{
  "hero": { "badge": "Nueva Temporada", "title1": "Vestí Tu", "title2": "Pasión", "subtitle": "Camisetas de fútbol originales de las mejores ligas del mundo.", "cta": "Explorar Colección", "stat1": "Camisetas", "stat2": "Ligas", "stat3": "Envío", "scrollDown": "Ir al catálogo" },
  "filters": { "all": "Todas las Ligas", "allTeams": "Todos los Equipos" },
  "catalog": { "subtitle": "VIVE TU PASIÓN", "title": "Encontrá tu camiseta", "promoBanner": "3x2 en todas las camisetas + Envío gratuito", "showing": "{count, plural, one {# camiseta} other {# camisetas}} disponibles", "empty": "No se encontraron camisetas para esta liga", "clearFilters": "Mostrar todas las camisetas" },
  "card": { "new": "Nuevo", "bestseller": "Más Vendido", "addToCart": "Agregar al Carrito", "customize": "Personalizar", "viewImage": "Ver imagen {index}" },

  "featured": { "bestsellers": "Más Vendidos", "newArrivals": "Novedades" },
  "promo": { "shipping": { "title": "Envío gratis", "description": "En compras 3x2" }, "quality": { "title": "Calidad garantizada", "description": "Clientes satisfechos" }, "delivery": { "title": "Entrega estimada", "description": "De 10 a 21 días" }, "returns": { "title": "Devoluciones fáciles", "description": "Política de 14 días" }, "payment": { "title": "Pago seguro", "description": "Transacciones encriptadas" } },
  "newsletter": { "title": "Quedate en el Juego", "description": "Suscribite para recibir lanzamientos exclusivos y descuentos especiales.", "placeholder": "Tu email", "submit": "Suscribirme", "privacy": "Respetamos tu privacidad. Podés darte de baja en cualquier momento." },
  "nav": { "home": "Inicio", "catalog": "Catálogo", "leagues": "Ligas", "contact": "Contacto" }
}